torchsparks/__init__.py
torchsparks/utils/__init__.py
torchsparks/utils/pythons.py
torchsparks/utils/shapes.py
torchsparks/utils/tensors.py
torchsparks-0.1.5.dist-info/LICENSE
torchsparks-0.1.5.dist-info/METADATA
torchsparks-0.1.5.dist-info/WHEEL
torchsparks-0.1.5.dist-info/top_level.txt
torchsparks-0.1.5.dist-info/RECORD
