Metadata-Version: 2.1
Name: torchsparks
Version: 0.1.5
Summary: Tools for PyTorch in Pure Python.
Home-page: https://github.com/chuanwise/torchsparks
Author: Chuanwise
Author-email: i@chuanwise.cn
License: Apache Software License
Classifier: Development Status :: 3 - Alpha
Classifier: Intended Audience :: Developers
Classifier: License :: OSI Approved :: Apache Software License
License-File: LICENSE
Requires-Dist: torch
